livekit/plugins/namo_turn_detector/__init__.py
livekit/plugins/namo_turn_detector/base.py
livekit/plugins/namo_turn_detector/download_model.py
livekit/plugins/namo_turn_detector/en_model.py
livekit/plugins/namo_turn_detector/language_specific.py
livekit/plugins/namo_turn_detector/log.py
livekit/plugins/namo_turn_detector/model.py
livekit/plugins/namo_turn_detector/multilingual.py
livekit/plugins/namo_turn_detector/py.typed
livekit/plugins/namo_turn_detector/version.py
livekit/plugins/namo_turn_detector/vi_model.py
livekit/plugins/namo_turn_detector/zh_model.py
livekit_plugins_namo_turn_detector-1.2.22.dist-info/METADATA
livekit_plugins_namo_turn_detector-1.2.22.dist-info/WHEEL
livekit_plugins_namo_turn_detector-1.2.22.dist-info/licenses/LICENSE
livekit_plugins_namo_turn_detector-1.2.22.dist-info/RECORD
