Metadata-Version: 2.4
Name: livekit-plugins-namo-turn-detector
Version: 1.2.22
Summary: End of utterance detection for LiveKit Agents
Project-URL: Documentation, https://docs.livekit.io
Project-URL: Website, https://livekit.io/
Project-URL: Source, https://github.com/livekit/agents
Author: dangvansam
License-Expression: Apache-2.0
License-File: LICENSE
Keywords: agent,ai,audio,livekit,videosdk
Classifier: Development Status :: 4 - Beta
Classifier: Intended Audience :: Developers
Classifier: Topic :: Communications :: Conferencing
Classifier: Topic :: Multimedia :: Sound/Audio
Classifier: Topic :: Multimedia :: Video
Classifier: Topic :: Scientific/Engineering :: Artificial Intelligence
Requires-Python: >=3.11
Requires-Dist: jinja2
Requires-Dist: livekit-agents>=1.2.18
Requires-Dist: numpy>=1.27
Requires-Dist: onnxruntime>=1.18
Requires-Dist: transformers>=4.47.1
